{
  "id": "m7fzziak3pak1waem6f",
  "seller": "test",
  "buyer": "z",
  "item": {
    "id": "m7cbm16w2p3be9gzu8u",
    "name": "Ammunition Box",
    "basePrice": 100,
    "count": 69,
    "totalPrice": 6900,
    "purchaseDate": "2025-02-19T19:43:04.328Z",
    "buyer": "death_man",
    "type": "countable",
    "section": "Equipment",
    "file": "m7cbm16w2p3be9gzu8u.json"
  },
  "count": 25,
  "price": 20,
  "status": "pending",
  "createdAt": "2025-02-22T09:28:42.332Z",
  "createdBy": "death_man"
}